{
    "save_1": [],
    "save_2": [],
    "save_3": [],
    "last": [
        {
            "x": 6,
            "y": 14,
            "direction": 3,
            "id": 1
        },
        {
            "x": 10,
            "y": 9,
            "direction": 3,
            "id": 2
        },
        {
            "x": 9,
            "y": 6,
            "direction": 2,
            "id": 3
        },
        {
            "x": 13,
            "y": 9,
            "direction": 1,
            "id": 4
        }
    ]
}